ycm/__init__.py
ycm/parse.py
ycm/yaff.js
ycm-0.1.71.data/scripts/yaff_compile.py
ycm-0.1.71.dist-info/DESCRIPTION.rst
ycm-0.1.71.dist-info/METADATA
ycm-0.1.71.dist-info/RECORD
ycm-0.1.71.dist-info/WHEEL
ycm-0.1.71.dist-info/metadata.json
ycm-0.1.71.dist-info/top_level.txt
