Metadata-Version: 2.0
Name: ycm
Version: 0.1.71
Summary: Compiler for the extended YAFF frontend framework
Home-page: https://www.d5research.com/
Author: Jack Cantrell-Warren
Author-email: jack@d5research.com
License: MIT
Keywords: yaff javascript js frontend framework compiler
Platform: UNKNOWN
Classifier: Development Status :: 3 - Alpha
Classifier: Intended Audience :: Developers
Classifier: Topic :: Software Development :: Build Tools
Classifier: License :: OSI Approved :: MIT License
Classifier: Programming Language :: Python :: 2
Classifier: Programming Language :: Python :: 2.7
